{
	"globalStyle": {
		"navigationBarBackgroundColor": "#fff",
		"navigationBarTextStyle": "black",
		"navigationBarTitleText": "导航栏"
	},
	"pages": [
		{
			"path": "pages/todo/index",
			"style": {
				"navigationBarTitleText": "待办"
			}
		},
		{
            "path" : "pages/todo/content",
            "style": {
            	"navigationBarTitleText": "所有待办"
            }
        },
		{
            "path" : "pages/doing/index",
            "style": {
            	"navigationBarTitleText": "待办集"
            }
        },
		{
		    "path" : "pages/calendar/index",
		    "style": {
		    	"navigationBarTitleText": "日历"
		    }
		},
		{
		    "path" : "pages/analysis/index",
		    "style": {
		    	"navigationBarTitleText": "统计"
		    }
		}
    ],
	"tabBar": {
		"color": "#000",
		"selectedColor": "#3366FF",
		"backgroundColor": "#fff",
		"list": [
			{
				"pagePath": "pages/todo/index",
				"text": "待办"
			},
			{
				"pagePath": "pages/doing/index",
				"text": "待办集"
			},
			{
				"pagePath": "pages/calendar/index",
				"text": "日历"
			},
			{
				"pagePath": "pages/analysis/index",
				"text": "统计"
			}
		]
	}
}
